__init__.py
pychainia.py
assets/Grasswalk.mp3
assets/cherrybomb.png
assets/peashooter.png
assets/potatomine.png
assets/sunflower.png
assets/walnut.png
pychainia-0.0.7.dist-info/LICENSE
pychainia-0.0.7.dist-info/METADATA
pychainia-0.0.7.dist-info/WHEEL
pychainia-0.0.7.dist-info/top_level.txt
pychainia-0.0.7.dist-info/RECORD
